ValidateBrackets.py
validate_brackets-0.0.3.dist-info/METADATA
validate_brackets-0.0.3.dist-info/WHEEL
validate_brackets-0.0.3.dist-info/licence.txt
validate_brackets-0.0.3.dist-info/top_level.txt
validate_brackets-0.0.3.dist-info/RECORD
