Metadata-Version: 2.1
Name: validate-brackets
Version: 0.0.3
Summary: validate brackets in a string
Home-page: 
Author: Amit Chojar
Author-email: pythonchojar@gmail.com
License: MIT
Platform: UNKNOWN
Classifier: License :: OSI Approved :: MIT License
Classifier: Programming Language :: Python :: 3
Classifier: Programming Language :: Python :: 3.6
Classifier: Programming Language :: Python :: 3.7
Classifier: Programming Language :: Python :: 3.8
License-File: licence.txt
Provides-Extra: dev
Requires-Dist: pytest (>=3.7) ; extra == 'dev'
